liftclient/__init__.py
liftclient/api_pb2.py
liftclient/api_pb2_grpc.py
liftclient/base.py
liftclient/errors.py
liftclient/liftclient.py
liftclient/message.py
liftclient/metadata.py
liftclient/python_liftbridge.py
liftclient/stream.py
liftclient/version.py
liftclient-0.0.6.dist-info/LICENSE.md
liftclient-0.0.6.dist-info/METADATA
liftclient-0.0.6.dist-info/WHEEL
liftclient-0.0.6.dist-info/top_level.txt
liftclient-0.0.6.dist-info/RECORD
