Metadata-Version: 2.1
Name: liftclient
Version: 0.0.6
Summary: Python client for Liftbridge.
Home-page: https://github.com/LaPetiteSouris/liftbridge
Author: GE
Author-email: sontunghoang@gmail.com
License: Apache Software License (Apache License, Version 2.0)
Platform: UNKNOWN
Classifier: Development Status :: 3 - Alpha
Classifier: Intended Audience :: Developers
Classifier: Natural Language :: English
Classifier: Programming Language :: Python :: 3.6
Classifier: Programming Language :: Python :: 3.7
Classifier: License :: OSI Approved :: Apache Software License
Classifier: Topic :: Software Development :: Libraries :: Python Modules
Classifier: Topic :: System :: Systems Administration
Classifier: Topic :: System :: Networking
Requires-Dist: grpcio (<2,>=1.23.0)
